cipher_solver/__init__.py
cipher_solver/cli.py
cipher_solver/consts.py
cipher_solver/simple.py
cipher_solver/utils.py
cipher_solver-1.0.2.dist-info/licenses/LICENSE
cipher_solver-1.0.2.dist-info/METADATA
cipher_solver-1.0.2.dist-info/WHEEL
cipher_solver-1.0.2.dist-info/entry_points.txt
cipher_solver-1.0.2.dist-info/top_level.txt
cipher_solver-1.0.2.dist-info/RECORD
