Metadata-Version: 2.4
Name: cipher_solver
Version: 1.0.2
Summary: Algorithm for solving simple, monoalphabetic substitution ciphers
Home-page: https://github.com/alimony/cipher_solver
Author: Markus Amalthea Magnuson
Author-email: markus@polyscopic.works
License: MIT
Project-URL: Documentation, https://alimony.github.io/cipher_solver/
Project-URL: Source, https://github.com/alimony/cipher_solver
Project-URL: Tracker, https://github.com/alimony/cipher_solver/issues
Keywords: monoalphabetic-substitution-cipher substitution-cipher cipher
Classifier: Development Status :: 5 - Production/Stable
Classifier: Intended Audience :: End Users/Desktop
Classifier: Intended Audience :: Developers
Classifier: Intended Audience :: Science/Research
Classifier: License :: OSI Approved :: MIT License
Classifier: Operating System :: OS Independent
Classifier: Programming Language :: Python
Classifier: Programming Language :: Python :: 3
Classifier: Programming Language :: Python :: 3 :: Only
Classifier: Programming Language :: Python :: 3.6
Classifier: Programming Language :: Python :: 3.7
Classifier: Programming Language :: Python :: 3.8
Classifier: Topic :: Scientific/Engineering :: Information Analysis
Classifier: Topic :: Security :: Cryptography
Classifier: Topic :: Text Processing :: Linguistic
Requires-Python: >=3.6
License-File: LICENSE
Requires-Dist: numpy
Dynamic: author
Dynamic: author-email
Dynamic: classifier
Dynamic: description
Dynamic: description-content-type
Dynamic: home-page
Dynamic: keywords
Dynamic: license
Dynamic: license-file
Dynamic: project-url
Dynamic: requires-dist
Dynamic: requires-python
Dynamic: summary
